<?xml version="1.0" encoding="utf-8"?>
<TextureAtlas imagePath="Menu_Tank.png">
	<!-- Created with Adobe Animate version 18.0.2.126 -->
	<!-- http://www.adobe.com/products/animate.html -->
	<SubTexture name="T Tank Idle0000" x="0" y="0" width="233" height="302"/>
	<SubTexture name="T Tank Idle0001" x="233" y="0" width="233" height="302"/>
	<SubTexture name="T Tank Idle0002" x="466" y="0" width="233" height="302"/>
	<SubTexture name="T Tank Idle0003" x="699" y="0" width="233" height="302"/>
	<SubTexture name="T Tank Idle0004" x="0" y="302" width="233" height="302"/>
	<SubTexture name="T Tank Idle0005" x="233" y="302" width="233" height="302"/>
	<SubTexture name="T Tank Idle0006" x="466" y="302" width="233" height="302"/>
	<SubTexture name="T Tank Idle0007" x="699" y="302" width="233" height="302"/>
	<SubTexture name="T Tank Idle0008" x="0" y="604" width="233" height="302"/>
	<SubTexture name="T Tank Idle0009" x="233" y="604" width="233" height="302"/>
	<SubTexture name="T Tank Idle0010" x="466" y="604" width="233" height="302"/>
</TextureAtlas>
